hvsampledata/__init__.py
hvsampledata/__init__.pyi
hvsampledata/__version.py
hvsampledata/_util.py
hvsampledata/_version.py
hvsampledata/py.typed
hvsampledata/_data/air_temperature_small.nc
hvsampledata/_data/apple_stocks.csv
hvsampledata/_data/earthquakes.csv
hvsampledata/_data/landsat_rgb.tif
hvsampledata/_data/penguins.csv
hvsampledata/_data/penguins.png
hvsampledata/_data/stocks.csv
hvsampledata/_data/us_states.geojson
hvsampledata-0.1.4.dist-info/METADATA
hvsampledata-0.1.4.dist-info/WHEEL
hvsampledata-0.1.4.dist-info/licenses/LICENSE.txt
hvsampledata-0.1.4.dist-info/RECORD
