Metadata-Version: 2.4
Name: hvsampledata
Version: 0.1.4
Summary: Datasets for the HoloViz projects
Author-email: HoloViz developers <developers@holoviz.org>
Maintainer-email: HoloViz developers <developers@holoviz.org>
License: BSD
License-File: LICENSE.txt
Classifier: Development Status :: 5 - Production/Stable
Classifier: Intended Audience :: Developers
Classifier: Intended Audience :: Science/Research
Classifier: License :: OSI Approved :: BSD License
Classifier: Natural Language :: English
Classifier: Operating System :: OS Independent
Classifier: Programming Language :: Python :: 3.9
Classifier: Programming Language :: Python :: 3.10
Classifier: Programming Language :: Python :: 3.11
Classifier: Programming Language :: Python :: 3.12
Classifier: Programming Language :: Python :: 3.13
Classifier: Topic :: Scientific/Engineering
Classifier: Topic :: Software Development :: Libraries
Requires-Python: >=3.9
Requires-Dist: platformdirs>=3.0.0
Requires-Dist: urllib3>=1.26.0
